progeval.py
test_progeval.py
progeval-1.0.0.dist-info/LICENSE
progeval-1.0.0.dist-info/METADATA
progeval-1.0.0.dist-info/WHEEL
progeval-1.0.0.dist-info/top_level.txt
progeval-1.0.0.dist-info/RECORD
