Metadata-Version: 2.1
Name: progeval
Version: 1.0.0
Summary: Cached lazy evaluation of computational trees
Author-email: Mathis Gerdes <mathisgerdes@gmail.com>
Classifier: Programming Language :: Python :: 3
Classifier: License :: OSI Approved :: MIT License
Classifier: Operating System :: OS Independent
Requires-Python: >=3.7
License-File: LICENSE
Requires-Dist: importlib-metadata ; python_version < "3.8"
